build/lib/build/lib/build/lib/cerulean_pond/__init__.py
build/lib/build/lib/build/lib/cerulean_pond/cerulean_pond.py
build/lib/build/lib/build/lib/tests/__init__.py
build/lib/build/lib/build/lib/tests/test_cerulean_pond.py
build/lib/build/lib/cerulean_pond/__init__.py
build/lib/build/lib/cerulean_pond/cerulean_pond.py
build/lib/build/lib/tests/__init__.py
build/lib/build/lib/tests/test_cerulean_pond.py
build/lib/cerulean_pond/__init__.py
build/lib/cerulean_pond/cerulean_pond.py
build/lib/tests/__init__.py
build/lib/tests/test_cerulean_pond.py
cerulean_pond/__init__.py
cerulean_pond/cerulean_pond.py
tests/__init__.py
tests/test_cerulean_pond.py
cerulean_pond-0.1.6.dist-info/LICENSE
cerulean_pond-0.1.6.dist-info/METADATA
cerulean_pond-0.1.6.dist-info/WHEEL
cerulean_pond-0.1.6.dist-info/top_level.txt
cerulean_pond-0.1.6.dist-info/RECORD
