Metadata-Version: 2.1
Name: cerulean_pond
Version: 0.1.6
Summary: A Python library to create data ponds, small datalakes.
Home-page: https://ceruleanpond.com
Author: Malik Houni
Author-email: Malik Houni <malik.datascience@gmail.com>
License: All Rights Reserved
Project-URL: homepage, https://ceruleanpond.com
Project-URL: repository, https://ceruleanpond.com
Keywords: data management,authentication,file uploads,server integration
Classifier: Programming Language :: Python :: 3
Classifier: License :: Other/Proprietary License
Classifier: Operating System :: OS Independent
Requires-Python: >=3.7
License-File: LICENSE
Requires-Dist: pandas (>=1.3.0)
Requires-Dist: requests (>=2.25.0)
Requires-Dist: bcrypt (>=3.2.0)
Requires-Dist: pyarrow
